README.rst
setup.py
XBRLAssembler.egg-info/PKG-INFO
XBRLAssembler.egg-info/SOURCES.txt
XBRLAssembler.egg-info/dependency_links.txt
XBRLAssembler.egg-info/top_level.txt
xbrlassembler/__init__.py
xbrlassembler/assembler.py
xbrlassembler/enums.py
xbrlassembler/error.py