Metadata-Version: 2.1
Name: XBRLAssembler
Version: 0.11.9
Summary: An assembler for XBRL Documents into pandas
Home-page: https://gitlab.com/Reggles44/xbrlassembler
Author: Reggles
Author-email: reginaldbeakes@gmail.com
License: UNKNOWN
Platform: UNKNOWN
Classifier: Programming Language :: Python :: 3
Classifier: Operating System :: OS Independent
